README.md
setup.py
CFGraph/__init__.py
CFGraph.egg-info/PKG-INFO
CFGraph.egg-info/SOURCES.txt
CFGraph.egg-info/dependency_links.txt
CFGraph.egg-info/requires.txt
CFGraph.egg-info/top_level.txt